LICENSE.txt
README.txt
setup.cfg
setup.py
sbcontrast/__init__.py
sbcontrast/__main__.py
sbcontrast/main.py
sbcontrast.egg-info/PKG-INFO
sbcontrast.egg-info/SOURCES.txt
sbcontrast.egg-info/dependency_links.txt
sbcontrast.egg-info/entry_points.txt
sbcontrast.egg-info/requires.txt
sbcontrast.egg-info/top_level.txt