Metadata-Version: 2.1
Name: sbcontrast
Version: 1.0.0
Summary: Surface Brightness Limit Calculator
Home-page: https://github.com/michaelkeim/sbcontrast/
Author: Keim, M. A., van Dokkum, P., Li, J.
Author-email: michael.keim@yale.edu
License: MIT
Download-URL: https://github.com/michaelkeim/sbcontrast/archive/master.tar.gz
Platform: UNKNOWN
Classifier: Development Status :: 1 - Planning
Classifier: Intended Audience :: Science/Research
Classifier: License :: OSI Approved :: MIT License
License-File: LICENSE.txt
